setup.py
amitu/__init__.py
amitu/zutils.py
amitu_zutils.egg-info/PKG-INFO
amitu_zutils.egg-info/SOURCES.txt
amitu_zutils.egg-info/dependency_links.txt
amitu_zutils.egg-info/namespace_packages.txt
amitu_zutils.egg-info/top_level.txt