Metadata-Version: 1.0
Name: amitu-zutils
Version: 0.1.0
Summary: Generic Utilities for ZMQ based services
Home-page: http://packages.python.org/amitu-zutils/
Author: Amit Upadhyay
Author-email: upadhyay@gmail.com
License: BSD
Platform: UNKNOWN
